resourceComponents/__init__.py
resourceComponents/bootstrap.py
resourceComponents/org_structure.py
resources/__init__.py
resources/apiService.py
resources/cloudStorage.py
resources/folder.py
resources/organization.py
resources/project.py
resources/serviceAccount.py
xangobolt_pulumi_gcp-0.0.1.dist-info/LICENSE
xangobolt_pulumi_gcp-0.0.1.dist-info/METADATA
xangobolt_pulumi_gcp-0.0.1.dist-info/WHEEL
xangobolt_pulumi_gcp-0.0.1.dist-info/top_level.txt
xangobolt_pulumi_gcp-0.0.1.dist-info/RECORD
