Metadata-Version: 2.1
Name: xangobolt-pulumi-gcp
Version: 0.0.1
Summary: Pulumi modules python package for GCP infrastructure as code
Home-page: https://github.com/pypa/sampleproject
Author: xangobolt
Author-email: sam4jones1@gmail.com
License: UNKNOWN
Project-URL: Bug Tracker, https://github.com/pypa/sampleproject/issues
Platform: UNKNOWN
Classifier: Programming Language :: Python :: 3
Classifier: License :: OSI Approved :: MIT License
Classifier: Operating System :: OS Independent
Requires-Python: >=3.9
License-File: LICENSE
